{
  "schema": 1,
  "entries": [
    {
      "origin": "https://github.com/expo/skills",
      "version": "v0.0.0-20260125144628-b631a6045b42",
      "rev": "b631a6045b421c425df947af74d3f6007e6ccc69"
    },
    {
      "origin": "https://github.com/jmmarotta/skills",
      "version": "v0.0.0-20260120144606-d207a9824281",
      "rev": "d207a9824281e6e16125975e5a7dde4ae837244b"
    },
    {
      "origin": "https://github.com/msmps/opentui-skill",
      "version": "v0.0.0-20260120104837-0cf21f653ffb",
      "rev": "0cf21f653ffbd089fe00ef3f2f1bd32672a536f3"
    }
  ]
}
